dpq/__init__.py
dpq/admin.py
dpq/apps.py
dpq/commands.py
dpq/decorators.py
dpq/models.py
dpq/queue.py
dpq/tests.py
dpq/migrations/0001_initial.py
dpq/migrations/0002_auto_20190419_2057.py
dpq/migrations/0003_alter_job_args.py
dpq/migrations/0004_job_failed.py
dpq/migrations/__init__.py
dpq_scheduler/__init__.py
dpq_scheduler/apps.py
dpq_scheduler/commands.py
dpq_scheduler/models.py
dpq_scheduler/schedules.py
dpq_scheduler/tests.py
dpq_scheduler/migrations/0001_initial.py
dpq_scheduler/migrations/__init__.py
makavafal_django_postgres_queue-1.0.5.dist-info/LICENSE
makavafal_django_postgres_queue-1.0.5.dist-info/METADATA
makavafal_django_postgres_queue-1.0.5.dist-info/WHEEL
makavafal_django_postgres_queue-1.0.5.dist-info/top_level.txt
makavafal_django_postgres_queue-1.0.5.dist-info/RECORD
