Metadata-Version: 2.1
Name: makavafal-django-postgres-queue
Version: 1.0.5
Home-page: https://github.com/majsvaffla/django-postgres-queue
Author: David Svenson
Author-email: davidsvenson@outlook.com
License: BSD
License-File: LICENSE
Requires-Dist: Django >=1.11
